coderbot_sim/__init__.py
coderbot_sim/flappy/__init__.py
coderbot_sim/flappy/sim.js
coderbot_sim/flappy/tk.py
coderbot_sim/flappy/widget.py
coderbot_sim/frogger/__init__.py
coderbot_sim/frogger/sim.js
coderbot_sim/frogger/tk.py
coderbot_sim/frogger/widget.py
coderbot_sim/mountain_car/__init__.py
coderbot_sim/mountain_car/sim.js
coderbot_sim/mountain_car/styles.css
coderbot_sim/mountain_car/tk.py
coderbot_sim/mountain_car/widget.py
coderbot_sim/simple_amr/__init__.py
coderbot_sim/simple_amr/example_maps.py
coderbot_sim/simple_amr/sim.js
coderbot_sim/simple_amr/styles.css
coderbot_sim/simple_amr/widget.py
coderbot_sim-0.0.8.dist-info/METADATA
coderbot_sim-0.0.8.dist-info/WHEEL
coderbot_sim-0.0.8.dist-info/top_level.txt
coderbot_sim-0.0.8.dist-info/RECORD
