Metadata-Version: 2.4
Name: coderbot-sim
Version: 0.0.8
Summary: starting robotics with simple simulation environments
Author-email: Matthew Taylor <matthew.taylor.andre@gmail.com>
Requires-Dist: anywidget
Requires-Dist: jupyter-ui-poll
